fwscan/__init__.py
fwscan/__main__.py
fwscan/logs.log
fwscan/py.typed
fwscan/scanners/checksec/__init__.py
fwscan/scanners/checksec/checksechelper.py
fwscan/scanners/checksec/checksecscanner.py
fwscan/scanners/radare/__init__py
fwscan/scanners/radare/r2stringscanner.py
fwscan/scanners/radare/stringscanner.py
fwscan/utils/__init__.py
fwscan/utils/console.py
fwscan-0.0.5.dist-info/entry_points.txt
fwscan-0.0.5.dist-info/LICENSE.rst
fwscan-0.0.5.dist-info/WHEEL
fwscan-0.0.5.dist-info/METADATA
fwscan-0.0.5.dist-info/RECORD
