Metadata-Version: 2.1
Name: fwscan
Version: 0.0.5
Summary: fwscan
Home-page: https://github.com/cpuinfo/fwscan
License: MIT
Author: CPU Info
Author-email: cpuinfo10@gmail.com
Requires-Python: >=3.6.1,<4.0.0
Classifier: Development Status :: 1 - Planning
Classifier: License :: OSI Approved :: MIT License
Classifier: Programming Language :: Python :: 3
Classifier: Programming Language :: Python :: 3.6
Classifier: Programming Language :: Python :: 3.7
Classifier: Programming Language :: Python :: 3.8
Classifier: Programming Language :: Python :: 3.9
Requires-Dist: click (>=8.0.1,<9.0.0)
Project-URL: Changelog, https://github.com/cpuinfo/fwscan/releases
Project-URL: Documentation, https://fwscan.readthedocs.io
Project-URL: Repository, https://github.com/cpuinfo/fwscan
